{
  "id": 5,
  "name": "錦見裕介",
  "furigana": "にしきみゆうすけ",
  "bloodType": "",
  "title": "株式会社マルトモ 代表取締役",
  "organization": "株式会社マルトモ",
  "hobby": "",
  "motto": "やるときはやる、遊ぶときは全力で遊ぶ",
  "image": "/img/no_image.png",
  "videoUrl": "/videos/person5-main.mp4",
  "officialSite": "https://example.com",
  "catchphrase": "やるときはやる、遊ぶときは全力で遊ぶ",
  "category": "製造業",
  "interviewNumber": 16,
  "articleTitle": "鋳物製造で地域を支える",
  "articleDescription": "1946年創業の鋳物メーカー三代目として、社員が誇りを持って働ける職場づくりを目指す。",
  "biography": "1946年創業の老舗鋳物メーカー「株式会社マルトモ」の三代目として、現場出身ならではの視点で組織を率いる。現在40歳で、社長に就任して10年目。\n\n創業者の孫にあたるが、もともとは継ぐ予定もなかったが、ある日突然「来月からお前がやれ」と言われ、現場から社長業へ転身。\n\n現場を知るからこそ、社員との距離感を何より大切にし、働く社員が安心して働ける職場、働く社員の家族が安心して送り出せる会社、働く人が誇りをもてる企業づくりを目指している。一緒に遊んだりもするが、締めるところはしっかり締める、メリハリある組織運営を意識。",
  "history": [
    {
      "year": "1946",
      "event": "株式会社マルトモ創業"
    },
    {
      "year": "10年前",
      "event": "代表取締役就任（3代目社長、当時30歳）"
    },
    {
      "year": "現在",
      "event": "鋳造から機械加工まで一貫生産体制、工作機械・産業機械の基礎部品製造"
    }
  ],
  "favorites": [
    {
      "category": "会社の強み",
      "item": "10kg未満の小物から8トン超の大型製品まで幅広く対応"
    },
    {
      "category": "経営理念",
      "item": "メリハリある社風で、社員が楽しく誇りを持って働ける職場づくり"
    }
  ],
  "schedule": [],
  "relatedPeople": [4]
}